{
	"$schema": "./node_modules/release-it/schema/release-it.json",
	"git": {
	  "commitMessage": "chore: release v${version}"
	},
	"github": {
	  "release": true
	},
	"npm": {
	  "publish": true
	},
	
	"plugins": {
	  "@release-it/conventional-changelog": {
	    "preset": "angular",
	    "infile": "CHANGELOG.md"
	  },
	  "release-it-changelogen": {
		"disableVersion": true,
		"templates": {
		  "commitMessage": "chore(release): v{{newVersion}}",
		  "tagMessage": "v{{newVersion}}",
		  "tagBody": "v{{newVersion}}"
		}
	  },
	  "git": {
		"tagName": "v${version}",
		"commitMessage": "chore(release): v${version}",
		"tagAnnotation": "v${version}"
	  }
	}
}